pntables/__init__.py
pntables/_version.py
pntables/pandas.py
pntables-0.1.0.dist-info/METADATA
pntables-0.1.0.dist-info/WHEEL
pntables-0.1.0.dist-info/licenses/LICENSE.txt
pntables-0.1.0.dist-info/RECORD
