Metadata-Version: 2.3
Name: pntables
Version: 0.1.0
Summary: Render Interactive DataFrames with Panel Tabulator.
Author-email: Demetris Roumis <m0hx8y3f6@mozmail.com>
License: BSD 3-Clause
License-File: LICENSE.txt
Classifier: License :: OSI Approved :: BSD License
Classifier: Operating System :: OS Independent
Classifier: Programming Language :: Python :: 3
Requires-Python: >=3.9
Requires-Dist: pandas
Requires-Dist: panel
Provides-Extra: testing
Requires-Dist: pytest; extra == 'testing'
